pyntree/__init__.py
pyntree/encryption.py
pyntree/errors.py
pyntree/file.py
pyntree-1.3.0.dist-info/LICENSE.txt
pyntree-1.3.0.dist-info/METADATA
pyntree-1.3.0.dist-info/WHEEL
pyntree-1.3.0.dist-info/top_level.txt
pyntree-1.3.0.dist-info/RECORD
