Metadata-Version: 2.1
Name: pyntree
Version: 1.3.0
Summary: pyntree is a python package which allows you to easily and syntactically save your data. Not only that, it also lets you save in multiple formats, and even serialize and compress data by merely changing a few characters.
Author-email: jvadair <dev@jvadair.com>
License: Apache License
Project-URL: Homepage, https://github.com/jvadair/pyntree
Project-URL: Documentation, https://pen.jvadair.com/books/pyntree
Keywords: database,pyntree,pyndb,python,encryption,crypto,cryptography,security,json,yaml,pickle,serial,compress,nosql
Classifier: License :: OSI Approved :: Apache Software License
Classifier: Programming Language :: Python
Classifier: Programming Language :: Python :: 3
Classifier: Operating System :: OS Independent
Classifier: Topic :: Database
Requires-Python: >=3.7.3
License-File: LICENSE.txt
Requires-Dist: compress-pickle >=2.1.0
Requires-Dist: pyyaml
Provides-Extra: dev
Requires-Dist: pipreqs ; extra == 'dev'
Requires-Dist: build ; extra == 'dev'
Requires-Dist: twine ; extra == 'dev'
Requires-Dist: requests ; extra == 'dev'
Provides-Extra: encryption
Requires-Dist: cryptography ; extra == 'encryption'
Requires-Dist: argon2-cffi ; extra == 'encryption'
Provides-Extra: lz4
Requires-Dist: compress-pickle[lz4] ; extra == 'lz4'
